{
  "mahasiswa": [
    {
      "id": "487e",
      "mahasiswa": [
        {
          "id": "1",
          "first_name": "Alia",
          "last_name": "Maulana Resti",
          "email": "aliamaulanaresti@mail.ugm.ac.id",
          "kelas": "A",
          "gender": "female",
          "latitude": -7.6926245,
          "longitude": 110.6718403
        }
      ]
    },
    {
      "id": "fe4d",
      "mahasiswa": [
        {
          "id": "2",
          "first_name": "Joseph",
          "last_name": "Damarseto",
          "email": "josephdamarseto@mail.ugm.ac.id",
          "kelas": "A",
          "gender": "male",
          "latitude": -7.6926245,
          "longitude": 110.6718403
        }
      ]
    }
  ]
}